panodac/__init__.py
panodac/hub.py
panodac/predictor.py
panodac/py.typed
panodac/seam_blending.py
panodac/utils.py
panodac/models/__init__.py
panodac/models/defattn_decoder.py
panodac/models/encoder.py
panodac/models/fpn_decoder.py
panodac/models/id_module.py
panodac/models/id_module_erp.py
panodac/models/idisc.py
panodac/models/idisc_erp.py
panodac/models/layers.py
panodac/models/backbones/__init__.py
panodac/models/backbones/resnet.py
panodac/models/backbones/swin.py
panodac/models/ops/__init__.py
panodac/models/ops/ms_deform_attn.py
panodac-0.1.1.dist-info/METADATA
panodac-0.1.1.dist-info/WHEEL
panodac-0.1.1.dist-info/licenses/LICENSE
panodac-0.1.1.dist-info/RECORD
