Metadata-Version: 2.4
Name: panodac
Version: 0.1.1
Summary: Plug-and-play metric depth estimation for any camera (perspective, fisheye, 360°). Based on Depth Any Camera (CVPR 2025).
Project-URL: Homepage, https://github.com/yuliangguo/depth_any_camera
Project-URL: Repository, https://github.com/YOUR_USERNAME/panodac
Project-URL: Documentation, https://github.com/YOUR_USERNAME/panodac#readme
Author: Yuliang Guo, Sparsh Garg
License: MIT License
License-File: LICENSE
Keywords: 360,computer-vision,depth-estimation,fisheye,monocular-depth,panorama,pytorch
Classifier: Development Status :: 4 - Beta
Classifier: Intended Audience :: Developers
Classifier: Intended Audience :: Science/Research
Classifier: License :: OSI Approved :: MIT License
Classifier: Operating System :: OS Independent
Classifier: Programming Language :: Python :: 3
Classifier: Programming Language :: Python :: 3.9
Classifier: Programming Language :: Python :: 3.10
Classifier: Programming Language :: Python :: 3.11
Classifier: Programming Language :: Python :: 3.12
Classifier: Topic :: Scientific/Engineering :: Artificial Intelligence
Classifier: Topic :: Scientific/Engineering :: Image Processing
Requires-Python: >=3.9
Requires-Dist: einops>=0.6.0
Requires-Dist: huggingface-hub>=0.20.0
Requires-Dist: numpy<2.0.0
Requires-Dist: opencv-python>=4.5.0
Requires-Dist: pillow>=9.0.0
Requires-Dist: scipy>=1.10.0
Requires-Dist: timm>=0.9.0
Requires-Dist: torch>=2.0.0
Requires-Dist: torchvision>=0.15.0
Provides-Extra: dev
Requires-Dist: pytest>=7.0.0; extra == 'dev'
Requires-Dist: ruff>=0.1.0; extra == 'dev'
Provides-Extra: docs
Requires-Dist: mkdocs-terminal>=4.6.0; extra == 'docs'
Requires-Dist: mkdocs>=1.5.0; extra == 'docs'
Requires-Dist: mkdocstrings[python]>=0.24.0; extra == 'docs'
Requires-Dist: pymdown-extensions>=10.0.0; extra == 'docs'
